work_journal/__init__.py
work_journal/cli.py
work_journal/config.ini
work_journal/config.py
work_journal/create.py
work_journal_cli-2.1.1.dist-info/LICENSE
work_journal_cli-2.1.1.dist-info/METADATA
work_journal_cli-2.1.1.dist-info/WHEEL
work_journal_cli-2.1.1.dist-info/entry_points.txt
work_journal_cli-2.1.1.dist-info/top_level.txt
work_journal_cli-2.1.1.dist-info/RECORD
