Metadata-Version: 2.1
Name: work-journal-cli
Version: 2.1.1
Summary: A CLI tool to schedule for writing a work journal with cron.
Home-page: https://github.com/hank-chouu/work-journal-cli
Author: Heng-Tse Chou
Author-email: hengtse.me@gmail.com
License: MIT
Keywords: Cron CLI
Classifier: Development Status :: 3 - Alpha
Classifier: Intended Audience :: End Users/Desktop
Classifier: Operating System :: Unix
Classifier: Programming Language :: Python :: 3
License-File: LICENSE
Requires-Dist: click
Requires-Dist: python-crontab
Requires-Dist: cron-descriptor
Requires-Dist: croniter
